src/cv2/__init__.py
src/cv2/config-3.py
src/cv2/config.py
src/cv2/load_config_py2.py
src/cv2/load_config_py3.py
src/cv2/version.py
src/cv2/data/__init__.py
src/cv2/gapi/__init__.py
src/cv2/mat_wrapper/__init__.py
src/cv2/misc/__init__.py
src/cv2/misc/version.py
utils/__init__.py
rudraa_cv2-0.3.dist-info/METADATA
rudraa_cv2-0.3.dist-info/WHEEL
rudraa_cv2-0.3.dist-info/licenses/LICENSE
rudraa_cv2-0.3.dist-info/RECORD
